{
  "dataset": "CHASEDB1",
  "image_id": "Image_11R",
  "image_path": "E:\\ca_apsrg_retinal_project\\data\\working_png\\CHASEDB1\\CHASEDB1\\Image_11R.png",
  "mask_path": "E:\\ca_apsrg_retinal_project\\data\\working_png\\CHASEDB1\\CHASEDB1\\Image_11R_1stHO.png",
  "fov_path": "",
  "pipeline_config": {
    "preprocessing": {
      "use_green_channel": true,
      "normalize_intensity": true,
      "apply_clahe": true,
      "clahe_clip_limit": 2.0,
      "clahe_tile_grid_size": [
        8,
        8
      ],
      "denoise_method": "median",
      "median_kernel_size": 3,
      "bilateral_d": 5,
      "bilateral_sigma_color": 50.0,
      "bilateral_sigma_space": 50.0,
      "apply_fov_mask": true
    },
    "apsrg_baseline": {
      "vessel_enhancement_method": "blackhat_multiscale",
      "vesselness_kernel_sizes": [
        7,
        11,
        15
      ],
      "seed_selection_method": "selective_fuzzy_harris",
      "seed_percentile": 92.0,
      "candidate_percentile": 78.0,
      "polling_window_size": 16,
      "polling_top_percentile": 97.0,
      "min_seed_distance": 2,
      "region_growing_connectivity": 8,
      "region_growing_mode": "edge_delayed",
      "max_intensity_difference": 18.0,
      "max_iterations": 500000,
      "edge_delayed_region_growing": {
        "enabled": true,
        "priority_mode": "kang_product",
        "fuzzy_distance_scale": 0.4,
        "connected_edge_wd": 0.4,
        "edge_floor": 0.05,
        "edge_weight": 0.35,
        "max_fuzzy_distance": 1.0,
        "recompute_priority": true,
        "priority_tolerance": 1e-06,
        "record_growth_order": true
      },
      "min_component_area": 8,
      "fill_small_holes_area": 8,
      "harris_seed": {
        "enabled": true,
        "block_size": 2,
        "ksize": 3,
        "k": 0.04,
        "response_threshold_ratio": 0.01,
        "nms_window_size": 3,
        "target_seed_count": 35,
        "min_seed_count": 7,
        "max_seed_count": 77,
        "prefer_vesselness_weight": 0.65,
        "use_candidate_constraint": true,
        "fallback_to_top_vesselness": true,
        "seed_dilate_radius": 0
      },
      "srg_features": {
        "enabled": true,
        "wd": 0.4,
        "ws": 0.4,
        "edge_window_size": 3,
        "similarity_window_size": 3,
        "threshold_mean_window_size": 5,
        "t_small": 0.75,
        "t_big": 0.95,
        "use_candidate_constraint": true,
        "use_fov_constraint": true,
        "fallback_to_ranked_score": true,
        "min_seed_pixels": 20,
        "max_seed_pixels": 5000,
        "seed_dilate_radius": 0
      },
      "hybrid_seed": {
        "enabled": true,
        "target_seed_count": 35,
        "min_seed_count": 7,
        "max_seed_count": 77,
        "fuzzy_support_radius": 2,
        "relaxed_support_radius": 5,
        "min_seed_distance": 3,
        "fuzzy_weight": 0.35,
        "harris_weight": 0.4,
        "vesselness_weight": 0.25,
        "use_candidate_constraint": true,
        "use_fov_constraint": true,
        "allow_relaxed_harris_fallback": true,
        "allow_fuzzy_fallback": true,
        "seed_dilate_radius": 0
      }
    },
    "adaptive_morphology": {
      "enabled": true,
      "remove_small_objects": true,
      "fill_small_holes": false,
      "closing_enabled": false,
      "opening_enabled": false,
      "skeleton_guard_enabled": true,
      "small_component_area_low_density": 8,
      "small_component_area_normal": 18,
      "small_component_area_high_density": 28,
      "hole_area_low_density": 4,
      "hole_area_normal": 8,
      "hole_area_high_density": 12,
      "closing_kernel_low_density": 0,
      "closing_kernel_normal": 0,
      "closing_kernel_high_density": 0,
      "opening_kernel_low_density": 0,
      "opening_kernel_normal": 0,
      "opening_kernel_high_density": 0,
      "low_density_threshold": 0.025,
      "high_density_threshold": 0.12,
      "skeleton_restore_radius": 1,
      "skeleton_min_component_length": 6
    },
    "ca_apsrg": {
      "enabled": true,
      "always_refine": true,
      "low_density_threshold": 0.025,
      "high_density_threshold": 0.12,
      "target_preserve_thin_vessels": true,
      "process_context": {
        "enabled": true,
        "can_trigger_refinement": true,
        "can_override_refinement_level": true,
        "low_seed_count": 7,
        "high_seed_count": 77,
        "high_candidate_density": 0.25,
        "high_connected_edge_density": 0.2,
        "connected_edge_threshold": 0.5,
        "high_growth_ratio": 600.0,
        "max_iterations_is_high_risk": true
      }
    },
    "context_features": {
      "small_component_area": 12,
      "connectivity": 8,
      "compute_skeleton_features": true,
      "resize_fov_to_mask": false
    },
    "evaluation": {
      "binary_threshold": 127,
      "evaluate_inside_fov_only": true,
      "resize_prediction_to_gt": true,
      "resize_fov_to_gt": true
    },
    "outputs": {
      "save_preprocessed": true,
      "save_apsrg_mask": true,
      "save_ca_apsrg_mask": true,
      "save_overlay": true,
      "save_side_by_side": true,
      "save_debug_json": true,
      "overlay_alpha": 0.45
    },
    "always_refine": true,
    "precision_threshold": 0.95
  },
  "apsrg_debug": {
    "vesselness": {
      "type": "ndarray",
      "shape": [
        960,
        999
      ],
      "dtype": "uint8",
      "min": 0.0,
      "max": 255.0,
      "sum": 9878380.0
    },
    "seeds": {
      "type": "ndarray",
      "shape": [
        960,
        999
      ],
      "dtype": "bool",
      "min": 0.0,
      "max": 1.0,
      "sum": 35.0
    },
    "candidate": {
      "type": "ndarray",
      "shape": [
        960,
        999
      ],
      "dtype": "bool",
      "min": 0.0,
      "max": 1.0,
      "sum": 122139.0
    },
    "grown_before_postprocess": {
      "type": "ndarray",
      "shape": [
        960,
        999
      ],
      "dtype": "bool",
      "min": 0.0,
      "max": 1.0,
      "sum": 13627.0
    },
    "seed_thr": 44.0,
    "candidate_thr": 24.0,
    "n_seed_pixels": 35,
    "n_candidate_pixels": 122139,
    "n_output_pixels": 13810,
    "seed_selection_debug": {
      "enabled": true,
      "fuzzy_debug": {
        "enabled": true,
        "connected_edge": {
          "type": "ndarray",
          "shape": [
            960,
            999
          ],
          "dtype": "float32",
          "min": 0.0,
          "max": 1.0,
          "sum": 53813.765625
        },
        "edge_intensity": {
          "type": "ndarray",
          "shape": [
            960,
            999
          ],
          "dtype": "float32",
          "min": 0.0,
          "max": 1.0,
          "sum": 50225.234375
        },
        "edge_direction": {
          "type": "ndarray",
          "shape": [
            960,
            999
          ],
          "dtype": "uint8",
          "min": 1.0,
          "max": 4.0,
          "sum": 1709871.0
        },
        "not_connected_edge": {
          "type": "ndarray",
          "shape": [
            960,
            999
          ],
          "dtype": "float32",
          "min": 0.0,
          "max": 1.0,
          "sum": 905226.25
        },
        "fuzzy_similarity": {
          "type": "ndarray",
          "shape": [
            960,
            999
          ],
          "dtype": "float32",
          "min": 0.3686758875846863,
          "max": 1.0,
          "sum": 931853.5
        },
        "fuzzy_threshold": {
          "type": "ndarray",
          "shape": [
            960,
            999
          ],
          "dtype": "float32",
          "min": 0.75,
          "max": 0.9166470766067505,
          "sum": 734844.625
        },
        "fuzzy_seed_score": {
          "type": "ndarray",
          "shape": [
            960,
            999
          ],
          "dtype": "float32",
          "min": 0.0,
          "max": 1.0,
          "sum": 905216.0
        },
        "fuzzy_srg_seeds": {
          "type": "ndarray",
          "shape": [
            960,
            999
          ],
          "dtype": "bool",
          "min": 0.0,
          "max": 1.0,
          "sum": 5000.0
        },
        "valid_seed_area": {
          "type": "ndarray",
          "shape": [
            960,
            999
          ],
          "dtype": "bool",
          "min": 0.0,
          "max": 1.0,
          "sum": 122139.0
        },
        "n_fuzzy_srg_seed_pixels": 5000,
        "n_valid_seed_area_pixels": 122139,
        "params": {
          "enabled": true,
          "wd": 0.4,
          "ws": 0.4,
          "edge_window_size": 3,
          "similarity_window_size": 3,
          "threshold_mean_window_size": 5,
          "t_small": 0.75,
          "t_big": 0.95,
          "use_candidate_constraint": true,
          "use_fov_constraint": true,
          "fallback_to_ranked_score": true,
          "min_seed_pixels": 20,
          "max_seed_pixels": 5000,
          "seed_dilate_radius": 0
        }
      },
      "harris_debug": {
        "enabled": true,
        "harris_response": {
          "type": "ndarray",
          "shape": [
            960,
            999
          ],
          "dtype": "float32",
          "min": 0.0,
          "max": 1.0,
          "sum": 108.59129333496094
        },
        "harris_candidates": {
          "type": "ndarray",
          "shape": [
            960,
            999
          ],
          "dtype": "bool",
          "min": 0.0,
          "max": 1.0,
          "sum": 424.0
        },
        "harris_selected_seeds": {
          "type": "ndarray",
          "shape": [
            960,
            999
          ],
          "dtype": "bool",
          "min": 0.0,
          "max": 1.0,
          "sum": 35.0
        },
        "harris_seed_scores_top": [
          0.5845445990562439,
          0.5692156553268433,
          0.5500794053077698,
          0.542702317237854,
          0.5236647725105286,
          0.520474374294281,
          0.49619144201278687,
          0.4867640733718872,
          0.4780210852622986,
          0.4738183617591858,
          0.4695579707622528,
          0.46903926134109497,
          0.45414048433303833,
          0.4437467157840729,
          0.44276753067970276,
          0.4375646412372589,
          0.43530839681625366,
          0.43496692180633545,
          0.43470311164855957,
          0.41543078422546387
        ],
        "n_harris_candidates": 424,
        "n_harris_seed_pixels": 35,
        "selected_seed_count": 35,
        "valid_seed_area_pixels": 122139,
        "params": {
          "enabled": true,
          "block_size": 2,
          "ksize": 3,
          "k": 0.04,
          "response_threshold_ratio": 0.01,
          "nms_window_size": 3,
          "target_seed_count": 35,
          "min_seed_count": 7,
          "max_seed_count": 77,
          "prefer_vesselness_weight": 0.65,
          "use_candidate_constraint": true,
          "fallback_to_top_vesselness": true,
          "seed_dilate_radius": 0
        }
      },
      "fuzzy_seed_support": {
        "type": "ndarray",
        "shape": [
          960,
          999
        ],
        "dtype": "bool",
        "min": 0.0,
        "max": 1.0,
        "sum": 5000.0
      },
      "strict_fuzzy_support": {
        "type": "ndarray",
        "shape": [
          960,
          999
        ],
        "dtype": "bool",
        "min": 0.0,
        "max": 1.0,
        "sum": 27796.0
      },
      "relaxed_fuzzy_support": {
        "type": "ndarray",
        "shape": [
          960,
          999
        ],
        "dtype": "bool",
        "min": 0.0,
        "max": 1.0,
        "sum": 58325.0
      },
      "harris_candidates": {
        "type": "ndarray",
        "shape": [
          960,
          999
        ],
        "dtype": "bool",
        "min": 0.0,
        "max": 1.0,
        "sum": 424.0
      },
      "strict_hybrid_candidates": {
        "type": "ndarray",
        "shape": [
          960,
          999
        ],
        "dtype": "bool",
        "min": 0.0,
        "max": 1.0,
        "sum": 1.0
      },
      "relaxed_hybrid_candidates": {
        "type": "ndarray",
        "shape": [
          960,
          999
        ],
        "dtype": "bool",
        "min": 0.0,
        "max": 1.0,
        "sum": 54.0
      },
      "fuzzy_local_maxima_fallback": {
        "type": "ndarray",
        "shape": [
          960,
          999
        ],
        "dtype": "bool",
        "min": 0.0,
        "max": 0.0,
        "sum": 0.0
      },
      "final_hybrid_candidate_pool": {
        "type": "ndarray",
        "shape": [
          960,
          999
        ],
        "dtype": "bool",
        "min": 0.0,
        "max": 1.0,
        "sum": 54.0
      },
      "hybrid_score": {
        "type": "ndarray",
        "shape": [
          960,
          999
        ],
        "dtype": "float32",
        "min": 0.028594760224223137,
        "max": 0.6215686798095703,
        "sum": 326553.6875
      },
      "hybrid_selected_seeds": {
        "type": "ndarray",
        "shape": [
          960,
          999
        ],
        "dtype": "bool",
        "min": 0.0,
        "max": 1.0,
        "sum": 35.0
      },
      "selected_coordinates": [
        [
          419,
          470
        ],
        [
          560,
          520
        ],
        [
          437,
          567
        ],
        [
          721,
          447
        ],
        [
          398,
          593
        ],
        [
          543,
          629
        ],
        [
          657,
          450
        ],
        [
          436,
          574
        ],
        [
          592,
          654
        ],
        [
          411,
          369
        ],
        [
          697,
          593
        ],
        [
          478,
          420
        ],
        [
          415,
          442
        ],
        [
          433,
          566
        ],
        [
          555,
          599
        ],
        [
          714,
          603
        ],
        [
          386,
          536
        ],
        [
          310,
          513
        ],
        [
          449,
          367
        ],
        [
          788,
          788
        ],
        [
          606,
          604
        ],
        [
          199,
          134
        ],
        [
          332,
          497
        ],
        [
          331,
          501
        ],
        [
          466,
          396
        ],
        [
          309,
          516
        ],
        [
          469,
          396
        ],
        [
          50,
          647
        ],
        [
          639,
          699
        ],
        [
          513,
          610
        ],
        [
          287,
          413
        ],
        [
          671,
          715
        ],
        [
          639,
          702
        ],
        [
          660,
          425
        ],
        [
          590,
          610
        ]
      ],
      "selected_scores": [
        0.45108526945114136,
        0.38831254839897156,
        0.3870191276073456,
        0.3860630393028259,
        0.3813161253929138,
        0.3745132386684418,
        0.3730582892894745,
        0.37152254581451416,
        0.37006473541259766,
        0.36292320489883423,
        0.35497617721557617,
        0.3548821210861206,
        0.35291212797164917,
        0.35038894414901733,
        0.34225380420684814,
        0.33931052684783936,
        0.339084267616272,
        0.33620813488960266,
        0.3300650715827942,
        0.32912835478782654,
        0.3279893398284912,
        0.3276047706604004,
        0.32758429646492004,
        0.3253743648529053,
        0.3234890103340149,
        0.3233802616596222,
        0.3201005756855011,
        0.3199882507324219,
        0.3198397159576416,
        0.31978490948677063,
        0.31804826855659485,
        0.3142971098423004,
        0.31213074922561646,
        0.3115147054195404,
        0.30938735604286194
      ],
      "fallback_stage": "relaxed_fuzzy_harris",
      "n_fuzzy_seed_pixels": 5000,
      "n_harris_candidates": 424,
      "n_strict_hybrid_candidates": 1,
      "n_final_hybrid_candidates": 54,
      "n_selected_seed_points": 35,
      "n_hybrid_seed_pixels": 35,
      "params": {
        "enabled": true,
        "target_seed_count": 35,
        "min_seed_count": 7,
        "max_seed_count": 77,
        "fuzzy_support_radius": 2,
        "relaxed_support_radius": 5,
        "min_seed_distance": 3,
        "fuzzy_weight": 0.35,
        "harris_weight": 0.4,
        "vesselness_weight": 0.25,
        "use_candidate_constraint": true,
        "use_fov_constraint": true,
        "allow_relaxed_harris_fallback": true,
        "allow_fuzzy_fallback": true,
        "seed_dilate_radius": 0
      },
      "method": "selective_fuzzy_harris"
    },
    "region_growing_debug": {
      "enabled": true,
      "mode": "edge_delayed",
      "priority_mode": "kang_product",
      "connected_edge": {
        "type": "ndarray",
        "shape": [
          960,
          999
        ],
        "dtype": "float32",
        "min": 0.0,
        "max": 1.0,
        "sum": 53813.765625
      },
      "edge_intensity": {
        "type": "ndarray",
        "shape": [
          960,
          999
        ],
        "dtype": "float32",
        "min": 0.0,
        "max": 1.0,
        "sum": 50225.234375
      },
      "edge_direction": {
        "type": "ndarray",
        "shape": [
          960,
          999
        ],
        "dtype": "uint8",
        "min": 1.0,
        "max": 4.0,
        "sum": 1709871.0
      },
      "region_labels": {
        "type": "ndarray",
        "shape": [
          960,
          999
        ],
        "dtype": "int32",
        "min": 0.0,
        "max": 35.0,
        "sum": 297506.0
      },
      "growth_order": {
        "type": "ndarray",
        "shape": [
          960,
          999
        ],
        "dtype": "int32",
        "min": 0.0,
        "max": 13593.0,
        "sum": 92391655.0
      },
      "n_initial_seed_pixels": 35,
      "n_initial_seed_components": 35,
      "n_candidate_pixels": 122139,
      "n_accepted_growth_pixels": 13592,
      "n_rejected_by_intensity": 11661,
      "n_rejected_by_fuzzy_distance": 0,
      "n_stale_queue_entries": 18921,
      "n_reprioritized_entries": 13403,
      "n_output_pixels": 13627,
      "iterations": 57577,
      "max_iterations_reached": false,
      "remaining_queue_size": 0,
      "final_region_means": {
        "1": 29.367346938775512,
        "2": 29.755725190839694,
        "3": 52.36186770428016,
        "4": 31.666666666666668,
        "5": 51.789855072463766,
        "6": 37.24263431542461,
        "7": 67.35,
        "8": 50.1030303030303,
        "9": 120.16176470588235,
        "10": 46.446516192345435,
        "11": 89.75,
        "12": 194.14285714285714,
        "13": 101.65384615384616,
        "14": 169.22916666666666,
        "15": 138.50228310502283,
        "16": 53.0625,
        "17": 61.54545454545455,
        "18": 34.21468926553672,
        "19": 36.797077922077925,
        "20": 39.319060773480665,
        "21": 108.08064516129032,
        "22": 36.34782608695652,
        "23": 72.10997963340122,
        "24": 38.05166051660517,
        "25": 117.2258064516129,
        "26": 62.3,
        "27": 78.63245823389022,
        "28": 52.480278422273784,
        "29": 89.44047619047619,
        "30": 47.454,
        "31": 63.426432291666664,
        "32": 97.28651685393258,
        "33": 118.17808219178082,
        "34": 136.3531746031746,
        "35": 37.61441213653603
      },
      "final_region_sizes": {
        "1": 49,
        "2": 131,
        "3": 514,
        "4": 6,
        "5": 138,
        "6": 577,
        "7": 20,
        "8": 165,
        "9": 68,
        "10": 1019,
        "11": 36,
        "12": 56,
        "13": 26,
        "14": 48,
        "15": 219,
        "16": 16,
        "17": 22,
        "18": 177,
        "19": 616,
        "20": 2172,
        "21": 248,
        "22": 713,
        "23": 491,
        "24": 813,
        "25": 124,
        "26": 30,
        "27": 419,
        "28": 862,
        "29": 84,
        "30": 500,
        "31": 1536,
        "32": 178,
        "33": 511,
        "34": 252,
        "35": 791
      },
      "params": {
        "enabled": true,
        "priority_mode": "kang_product",
        "fuzzy_distance_scale": 0.4,
        "connected_edge_wd": 0.4,
        "edge_floor": 0.05,
        "edge_weight": 0.35,
        "max_fuzzy_distance": 1.0,
        "recompute_priority": true,
        "priority_tolerance": 1e-06,
        "record_growth_order": true
      }
    },
    "params": {
      "vessel_enhancement_method": "blackhat_multiscale",
      "vesselness_kernel_sizes": [
        7,
        11,
        15
      ],
      "seed_selection_method": "selective_fuzzy_harris",
      "seed_percentile": 92.0,
      "candidate_percentile": 78.0,
      "polling_window_size": 16,
      "polling_top_percentile": 97.0,
      "min_seed_distance": 2,
      "region_growing_connectivity": 8,
      "region_growing_mode": "edge_delayed",
      "max_intensity_difference": 18.0,
      "max_iterations": 500000,
      "edge_delayed_region_growing": {
        "enabled": true,
        "priority_mode": "kang_product",
        "fuzzy_distance_scale": 0.4,
        "connected_edge_wd": 0.4,
        "edge_floor": 0.05,
        "edge_weight": 0.35,
        "max_fuzzy_distance": 1.0,
        "recompute_priority": true,
        "priority_tolerance": 1e-06,
        "record_growth_order": true
      },
      "min_component_area": 8,
      "fill_small_holes_area": 8,
      "harris_seed": {
        "enabled": true,
        "block_size": 2,
        "ksize": 3,
        "k": 0.04,
        "response_threshold_ratio": 0.01,
        "nms_window_size": 3,
        "target_seed_count": 35,
        "min_seed_count": 7,
        "max_seed_count": 77,
        "prefer_vesselness_weight": 0.65,
        "use_candidate_constraint": true,
        "fallback_to_top_vesselness": true,
        "seed_dilate_radius": 0
      },
      "srg_features": {
        "enabled": true,
        "wd": 0.4,
        "ws": 0.4,
        "edge_window_size": 3,
        "similarity_window_size": 3,
        "threshold_mean_window_size": 5,
        "t_small": 0.75,
        "t_big": 0.95,
        "use_candidate_constraint": true,
        "use_fov_constraint": true,
        "fallback_to_ranked_score": true,
        "min_seed_pixels": 20,
        "max_seed_pixels": 5000,
        "seed_dilate_radius": 0
      },
      "hybrid_seed": {
        "enabled": true,
        "target_seed_count": 35,
        "min_seed_count": 7,
        "max_seed_count": 77,
        "fuzzy_support_radius": 2,
        "relaxed_support_radius": 5,
        "min_seed_distance": 3,
        "fuzzy_weight": 0.35,
        "harris_weight": 0.4,
        "vesselness_weight": 0.25,
        "use_candidate_constraint": true,
        "use_fov_constraint": true,
        "allow_relaxed_harris_fallback": true,
        "allow_fuzzy_fallback": true,
        "seed_dilate_radius": 0
      }
    }
  },
  "ca_apsrg_debug": {
    "enabled": true,
    "context_features": {
      "vessel_density": 0.014399816483149816,
      "vessel_pixel_count": 13810,
      "valid_area_pixel_count": 959040,
      "component_count": 18,
      "mean_component_area": 767.2222222222222,
      "median_component_area": 273.5,
      "std_component_area": 1572.7747085805445,
      "min_component_area": 16,
      "max_component_area": 7090,
      "small_component_count": 0,
      "small_component_ratio": 0.0,
      "small_component_area_total": 0,
      "small_component_area_ratio": 0.0,
      "largest_component_area": 7090,
      "largest_component_area_ratio": 0.5133960897900073,
      "skeleton_pixel_count": 3789,
      "skeleton_to_vessel_ratio": 0.27436640115858074,
      "endpoint_count": 155,
      "branchpoint_count": 668,
      "endpoint_density": 0.0409078912641858,
      "branchpoint_density": 0.1762998152546846,
      "density_level": "low",
      "noise_level": "low",
      "recommended_refinement_level": "conservative"
    },
    "effective_context_features": {
      "vessel_density": 0.014399816483149816,
      "vessel_pixel_count": 13810,
      "valid_area_pixel_count": 959040,
      "component_count": 18,
      "mean_component_area": 767.2222222222222,
      "median_component_area": 273.5,
      "std_component_area": 1572.7747085805445,
      "min_component_area": 16,
      "max_component_area": 7090,
      "small_component_count": 0,
      "small_component_ratio": 0.0,
      "small_component_area_total": 0,
      "small_component_area_ratio": 0.0,
      "largest_component_area": 7090,
      "largest_component_area_ratio": 0.5133960897900073,
      "skeleton_pixel_count": 3789,
      "skeleton_to_vessel_ratio": 0.27436640115858074,
      "endpoint_count": 155,
      "branchpoint_count": 668,
      "endpoint_density": 0.0409078912641858,
      "branchpoint_density": 0.1762998152546846,
      "density_level": "low",
      "noise_level": "low",
      "recommended_refinement_level": "conservative"
    },
    "apsrg_process_context": {
      "seed_selection_method": "selective_fuzzy_harris",
      "region_growing_mode": "edge_delayed",
      "valid_area_pixel_count": 959040,
      "seed_pixel_count": 35,
      "selected_seed_point_count": 35,
      "candidate_pixel_count": 122139,
      "output_pixel_count": 13810,
      "seed_density": 3.6494828161494826e-05,
      "candidate_density": 0.12735548048048048,
      "output_density": 0.014399816483149816,
      "growth_ratio": 394.57142857142856,
      "fuzzy_seed_pixel_count": 5000,
      "harris_candidate_count": 424,
      "strict_hybrid_candidate_count": 1,
      "initial_seed_component_count": 35,
      "accepted_growth_pixel_count": 13592,
      "connected_edge_mean": 0.05611211806535721,
      "connected_edge_density": 0.002679763096429763,
      "max_iterations_reached": false,
      "process_risk_score": 0,
      "process_risk_level": "low",
      "recommended_refinement_level": "normal"
    },
    "mask_refinement_level": "conservative",
    "process_refinement_level": "normal",
    "combined_refinement_level": "conservative",
    "refined_context_features": {
      "vessel_density": 0.014399816483149816,
      "vessel_pixel_count": 13810,
      "valid_area_pixel_count": 959040,
      "component_count": 18,
      "mean_component_area": 767.2222222222222,
      "median_component_area": 273.5,
      "std_component_area": 1572.7747085805445,
      "min_component_area": 16,
      "max_component_area": 7090,
      "small_component_count": 0,
      "small_component_ratio": 0.0,
      "small_component_area_total": 0,
      "small_component_area_ratio": 0.0,
      "largest_component_area": 7090,
      "largest_component_area_ratio": 0.5133960897900073,
      "skeleton_pixel_count": 3789,
      "skeleton_to_vessel_ratio": 0.27436640115858074,
      "endpoint_count": 155,
      "branchpoint_count": 668,
      "endpoint_density": 0.0409078912641858,
      "branchpoint_density": 0.1762998152546846,
      "density_level": "low",
      "noise_level": "low",
      "recommended_refinement_level": "conservative"
    },
    "refinement_debug": {
      "enabled": true,
      "context_features": {
        "vessel_density": 0.014399816483149816,
        "vessel_pixel_count": 13810,
        "valid_area_pixel_count": 959040,
        "component_count": 18,
        "mean_component_area": 767.2222222222222,
        "median_component_area": 273.5,
        "std_component_area": 1572.7747085805445,
        "min_component_area": 16,
        "max_component_area": 7090,
        "small_component_count": 0,
        "small_component_ratio": 0.0,
        "small_component_area_total": 0,
        "small_component_area_ratio": 0.0,
        "largest_component_area": 7090,
        "largest_component_area_ratio": 0.5133960897900073,
        "skeleton_pixel_count": 3789,
        "skeleton_to_vessel_ratio": 0.27436640115858074,
        "endpoint_count": 155,
        "branchpoint_count": 668,
        "endpoint_density": 0.0409078912641858,
        "branchpoint_density": 0.1762998152546846,
        "density_level": "low",
        "noise_level": "low",
        "recommended_refinement_level": "conservative"
      },
      "refined_context_features": {
        "vessel_density": 0.014399816483149816,
        "vessel_pixel_count": 13810,
        "valid_area_pixel_count": 959040,
        "component_count": 18,
        "mean_component_area": 767.2222222222222,
        "median_component_area": 273.5,
        "std_component_area": 1572.7747085805445,
        "min_component_area": 16,
        "max_component_area": 7090,
        "small_component_count": 0,
        "small_component_ratio": 0.0,
        "small_component_area_total": 0,
        "small_component_area_ratio": 0.0,
        "largest_component_area": 7090,
        "largest_component_area_ratio": 0.5133960897900073,
        "skeleton_pixel_count": 3789,
        "skeleton_to_vessel_ratio": 0.27436640115858074,
        "endpoint_count": 155,
        "branchpoint_count": 668,
        "endpoint_density": 0.0409078912641858,
        "branchpoint_density": 0.1762998152546846,
        "density_level": "low",
        "noise_level": "low",
        "recommended_refinement_level": "conservative"
      },
      "selected_parameters": {
        "refinement_level": "conservative",
        "density_level": "low",
        "noise_level": "low",
        "min_component_area": 8,
        "hole_area": 4,
        "closing_kernel_size": 0,
        "opening_kernel_size": 0,
        "use_opening": false,
        "use_closing": false,
        "use_skeleton_guard": true
      },
      "config": {
        "enabled": true,
        "remove_small_objects": true,
        "fill_small_holes": false,
        "closing_enabled": false,
        "opening_enabled": false,
        "skeleton_guard_enabled": true,
        "small_component_area_low_density": 8,
        "small_component_area_normal": 18,
        "small_component_area_high_density": 28,
        "hole_area_low_density": 4,
        "hole_area_normal": 8,
        "hole_area_high_density": 12,
        "closing_kernel_low_density": 0,
        "closing_kernel_normal": 0,
        "closing_kernel_high_density": 0,
        "opening_kernel_low_density": 0,
        "opening_kernel_normal": 0,
        "opening_kernel_high_density": 0,
        "low_density_threshold": 0.025,
        "high_density_threshold": 0.12,
        "skeleton_restore_radius": 1,
        "skeleton_min_component_length": 6
      },
      "intermediate_masks": {
        "baseline": {
          "type": "ndarray",
          "shape": [
            960,
            999
          ],
          "dtype": "bool",
          "min": 0.0,
          "max": 1.0,
          "sum": 13810.0
        },
        "after_remove_small_objects": {
          "type": "ndarray",
          "shape": [
            960,
            999
          ],
          "dtype": "bool",
          "min": 0.0,
          "max": 1.0,
          "sum": 13810.0
        },
        "after_skeleton_guard": {
          "type": "ndarray",
          "shape": [
            960,
            999
          ],
          "dtype": "bool",
          "min": 0.0,
          "max": 1.0,
          "sum": 13810.0
        }
      },
      "n_pixels_before": 13810,
      "n_pixels_after": 13810,
      "n_pixels_removed": 0,
      "n_pixels_added": 0
    },
    "ca_apsrg_config": {
      "enabled": true,
      "always_refine": true,
      "low_density_threshold": 0.025,
      "high_density_threshold": 0.12,
      "target_preserve_thin_vessels": true,
      "process_context": {
        "enabled": true,
        "can_trigger_refinement": true,
        "can_override_refinement_level": true,
        "low_seed_count": 7,
        "high_seed_count": 77,
        "high_candidate_density": 0.25,
        "high_connected_edge_density": 0.2,
        "connected_edge_threshold": 0.5,
        "high_growth_ratio": 600.0,
        "max_iterations_is_high_risk": true
      }
    },
    "n_baseline_pixels": 13810,
    "n_refined_pixels": 13810,
    "n_pixels_removed": 0,
    "n_pixels_added": 0
  },
  "saved_paths": {
    "preprocessed_path": "E:\\ca_apsrg_retinal_project\\outputs\\method_ablation\\experiments_a07_process_context_override\\CHASEDB1\\preprocessed\\Image_11R_preprocessed.png",
    "baseline_mask_path": "E:\\ca_apsrg_retinal_project\\outputs\\method_ablation\\experiments_a07_process_context_override\\CHASEDB1\\baseline_masks\\Image_11R_apsrg_baseline.png",
    "ca_apsrg_mask_path": "E:\\ca_apsrg_retinal_project\\outputs\\method_ablation\\experiments_a07_process_context_override\\CHASEDB1\\ca_apsrg_masks\\Image_11R_ca_apsrg.png",
    "baseline_overlay_path": "E:\\ca_apsrg_retinal_project\\outputs\\method_ablation\\experiments_a07_process_context_override\\CHASEDB1\\overlays\\Image_11R_baseline_overlay.png",
    "ca_apsrg_overlay_path": "E:\\ca_apsrg_retinal_project\\outputs\\method_ablation\\experiments_a07_process_context_override\\CHASEDB1\\overlays\\Image_11R_ca_apsrg_overlay.png",
    "comparison_path": "E:\\ca_apsrg_retinal_project\\outputs\\method_ablation\\experiments_a07_process_context_override\\CHASEDB1\\comparison\\Image_11R_comparison.png"
  }
}